yinyang_base64/__init__.py
yinyang_base64/main.py
yinyang_base64-1.0.1.dist-info/METADATA
yinyang_base64-1.0.1.dist-info/WHEEL
yinyang_base64-1.0.1.dist-info/top_level.txt
yinyang_base64-1.0.1.dist-info/RECORD
