Metadata-Version: 2.1
Name: yinyang-base64
Version: 1.0.1
Summary: Base64 but Kanji (Yinyang) characters.
Home-page: https://github.com/Lionel-Kyo/YinYangBase64
License: MIT
Requires-Python: >= 3.9
